README.md
setup.py
megaboost/__init__.py
megaboost/augmentation.py
megaboost/autoaugment.py
megaboost/data.py
megaboost/main.py
megaboost/model.py
megaboost/parser_setting.py
megaboost/public.py
megaboost/torch_custom_dataset.py
megaboost/utils.py
megaboost.egg-info/PKG-INFO
megaboost.egg-info/SOURCES.txt
megaboost.egg-info/dependency_links.txt
megaboost.egg-info/requires.txt
megaboost.egg-info/top_level.txt